vmfinder/__init__.py
vmfinder/cli.py
vmfinder/cloud_image.py
vmfinder/cloud_init.py
vmfinder/completion.py
vmfinder/config.py
vmfinder/default_templates.py
vmfinder/disk.py
vmfinder/logger.py
vmfinder/template.py
vmfinder/virtiofsd.py
vmfinder/vm_manager.py
vmfinder/commands/__init__.py
vmfinder/commands/init.py
vmfinder/commands/install_completion.py
vmfinder/commands/template.py
vmfinder/commands/virtiofs.py
vmfinder/commands/vm/__init__.py
vmfinder/commands/vm/access.py
vmfinder/commands/vm/basic.py
vmfinder/commands/vm/cloud_init.py
vmfinder/commands/vm/config.py
vmfinder/commands/vm/manage.py
vmfinder-0.2.1.dist-info/licenses/LICENSE
vmfinder-0.2.1.dist-info/METADATA
vmfinder-0.2.1.dist-info/WHEEL
vmfinder-0.2.1.dist-info/entry_points.txt
vmfinder-0.2.1.dist-info/top_level.txt
vmfinder-0.2.1.dist-info/RECORD
