Metadata-Version: 2.4
Name: vmfinder
Version: 0.2.1
Summary: A libvirt-based VM management tool
Author-email: wheatfox <wheatfox17@icloud.com>
Maintainer-email: wheatfox <wheatfox17@icloud.com>
License: MIT License
Project-URL: Homepage, https://github.com/enkerewpo/vmfinder
Project-URL: Repository, https://github.com/enkerewpo/vmfinder
Project-URL: Issues, https://github.com/enkerewpo/vmfinder/issues
Project-URL: Documentation, https://github.com/enkerewpo/vmfinder/blob/main/README.md
Keywords: libvirt,vm,virtualization,cloud,virtualization management
Classifier: Development Status :: 3 - Alpha
Classifier: Intended Audience :: Developers
Classifier: Programming Language :: Python :: 3
Classifier: Programming Language :: Python :: 3.8
Classifier: Programming Language :: Python :: 3.9
Classifier: Programming Language :: Python :: 3.10
Classifier: Programming Language :: Python :: 3.11
Requires-Python: >=3.8
License-File: LICENSE
Requires-Dist: libvirt-python>=11.8.0
Requires-Dist: pyyaml>=6.0
Requires-Dist: jinja2>=3.1.0
Requires-Dist: tabulate>=0.9.0
Requires-Dist: argcomplete>=3.0.0
Requires-Dist: requests>=2.25.0
Dynamic: license-file
